gredisql/__init__.py
gredisql/core.py
gredisql-0.0.11.dist-info/LICENSE.txt
gredisql-0.0.11.dist-info/METADATA
gredisql-0.0.11.dist-info/WHEEL
gredisql-0.0.11.dist-info/top_level.txt
gredisql-0.0.11.dist-info/RECORD
