Metadata-Version: 2.1
Name: gredisql
Version: 0.0.11
Summary: A GraphQL interface for Redis Database. 
Home-page: https://github.com/sabbiramin113008/gredisql
Author: Sabbir Amin
Author-email: sabbiramin.cse11ruet@gmail.com
License: MIT
Keywords: python,Database,Redis,GraphQL
Classifier: License :: OSI Approved :: MIT License
Classifier: Programming Language :: Python
Classifier: Operating System :: OS Independent
Classifier: Topic :: Utilities
License-File: LICENSE.txt
Requires-Dist: redis ==5.0.0
Requires-Dist: Flask ==2.3.3
Requires-Dist: strawberry-graphql ==0.205.0
